LICENSE
README.md
setup.py
tpu_pod_commander/__init__.py
tpu_pod_commander/cli.py
tpu_pod_commander.egg-info/PKG-INFO
tpu_pod_commander.egg-info/SOURCES.txt
tpu_pod_commander.egg-info/dependency_links.txt
tpu_pod_commander.egg-info/entry_points.txt
tpu_pod_commander.egg-info/requires.txt
tpu_pod_commander.egg-info/top_level.txt